python_pkg/__init__.py
python_pkg/frases.py
python_pkg-0.0.2.dist-info/METADATA
python_pkg-0.0.2.dist-info/RECORD
python_pkg-0.0.2.dist-info/WHEEL
python_pkg-0.0.2.dist-info/top_level.txt
