Metadata-Version: 2.1
Name: python-pkg
Version: 0.0.2
Summary: Un paquete de NLTK y Scrapy por SEO
Home-page: https://github.com/pypa/sampleproject
Author: Noelle Rivera
Author-email: noelle.rivera.516@gmail.com
License: UNKNOWN
Platform: UNKNOWN
Classifier: Programming Language :: Python :: 3
Classifier: License :: OSI Approved :: MIT License
Classifier: Operating System :: OS Independent
